ngbdemosdk/LiveClient.py
ngbdemosdk/__init__.py
ngbdemosdk/response/ApiResponse.py
ngbdemosdk/response/__init__.py
nbgdomosdk-1.0.dist-info/LICENSE
nbgdomosdk-1.0.dist-info/METADATA
nbgdomosdk-1.0.dist-info/WHEEL
nbgdomosdk-1.0.dist-info/top_level.txt
nbgdomosdk-1.0.dist-info/RECORD
